{
  "dimensions": "930x1491",
  "product_type": "USB Hub",
  "brand_category": "UGREEN",
  "industry_category": "Electronics / Tech",
  "ad_format": "Social Post",
  "target_audience": "Tech enthusiasts, students, professionals (20-45 years old), both genders",
  "color_scheme": "Blue, black, white, cool tones, modern",
  "text_density": "Minimal",
  "composition": "Product-focused",
  "cta_type": "None",
  "marketing_objective": "Awareness",
  "visual_style": "Minimalist, elegant",
  "special_elements": "Product features (Ultra-slim 4-Port USB3.0 hub)",
  "file_name": "electronic_product_print_ads_112.jpg",
  "file_path": "D:/Developer/FunTime/AdGen/image-label/images/source\\electronic\\electronic_product_print_ads_112.jpg",
  "width": 930,
  "height": 1491
}