{
  "dimensions": "618x900",
  "product_type": "Smartphone (iPhone)",
  "brand_category": "Apple",
  "industry_category": "Electronics / Tech",
  "ad_format": "Social Post",
  "target_audience": "16-45, Tech enthusiasts, General consumers",
  "color_scheme": "White, Light Blue, Neutral Tones, Clean",
  "text_density": "Minimal",
  "composition": "Product-focused",
  "cta_type": "None",
  "marketing_objective": "Awareness",
  "visual_style": "Minimalist, Modern, Clean",
  "special_elements": "None",
  "file_name": "electronic_product_print_ads_61.jpg",
  "file_path": "D:/Developer/FunTime/AdGen/image-label/images/source\\electronic\\electronic_product_print_ads_61.jpg",
  "width": 618,
  "height": 900
}