{
  "dimensions": "1000x1499",
  "product_type": "Yoga apparel (leggings and sports bra)",
  "brand_category": "Lululemon",
  "industry_category": "Fashion",
  "ad_format": "Social post",
  "target_audience": "Women, 20-40, interested in fitness, yoga, and athleisure wear",
  "color_scheme": "Blue, yellow, red, and beige. Energetic and vibrant.",
  "text_density": "Moderate",
  "composition": "Lifestyle, product-focused",
  "cta_type": "Implied (visit website/store)",
  "marketing_objective": "Awareness",
  "visual_style": "Bold, modern, active",
  "special_elements": "Product line name (Align), brand logo, payment option (Klarna)",
  "file_name": "Fitness_product_print_ads_69.jpg",
  "file_path": "D:/Developer/FunTime/AdGen/image-label/images/source\\fitness\\Fitness_product_print_ads_69.jpg",
  "width": 1000,
  "height": 1499
}