{
  "dimensions": "1080x1080",
  "product_type": "Gym Membership/Services",
  "brand_category": "Gold's Gym",
  "industry_category": "Fitness / Wellness",
  "ad_format": "Social Post",
  "target_audience": "20-45 year olds, both genders, fitness enthusiasts",
  "color_scheme": "Yellow, Black, Gray, Motivational",
  "text_density": "Moderate",
  "composition": "Lifestyle",
  "cta_type": "None",
  "marketing_objective": "Awareness",
  "visual_style": "Bold",
  "special_elements": "Motivational quote",
  "file_name": "Fitness_product_print_ads_38.jpg",
  "file_path": "D:/Developer/FunTime/AdGen/image-label/images/source\\fitness\\Fitness_product_print_ads_38.jpg",
  "width": 1080,
  "height": 1080
}