{
  "dimensions": "720x1280",
  "product_type": "Ready-to-cook meal kits (Goan Fish Curry, Sambar Mix)",
  "brand_category": "Meal Umm",
  "industry_category": "Food / Beverage",
  "ad_format": "Social post",
  "target_audience": "Adults (25-55), busy professionals, cooking enthusiasts, people interested in convenience meals",
  "color_scheme": "Yellow, red, green, white, orange. Warm and inviting.",
  "text_density": "Moderate",
  "composition": "Product-focused, showcasing the packaging and a phone displaying the product.",
  "cta_type": "Implied (Visit website/app)",
  "marketing_objective": "Awareness",
  "visual_style": "Playful, modern, clean",
  "special_elements": "Product names, brand logo, tagline, chef's hat graphic, claim of 'Meals Minus Grind'",
  "file_name": "food_print_ads_20250401140900_062.jpg",
  "file_path": "D:/Developer/FunTime/AdGen/image-label/images/source\\food-beverages\\food_print_ads_20250401140900_062.jpg",
  "width": 720,
  "height": 1280
}