{
  "dimensions": "1280x1658",
  "product_type": "Health Alerts App",
  "brand_category": "American EHR",
  "industry_category": "Healthcare",
  "ad_format": "Social Post",
  "target_audience": "Adults, Health-conscious individuals",
  "color_scheme": "Dark, muted tones, brown, white, silver, creating a serious and slightly ominous mood.",
  "text_density": "Minimal",
  "composition": "Product-focused, conceptual. The grenade on the doorknob is a metaphor for the danger of germs.",
  "cta_type": "Implied (Download/Use the App)",
  "marketing_objective": "Awareness",
  "visual_style": "Bold, impactful, slightly alarming",
  "special_elements": "Metaphorical imagery (grenade = germs), app logo",
  "file_name": "Healthcare_product_print_ad_9.jpg",
  "file_path": "D:/Developer/FunTime/AdGen/image-label/images/source\\healthcare\\Healthcare_product_print_ad_9.jpg",
  "width": 1280,
  "height": 1658
}