{
  "dimensions": "736x1104",
  "product_type": "Collagen Superfruit Gummies",
  "brand_category": "Goli Nutrition",
  "industry_category": "Beauty / Personal Care",
  "ad_format": "Social Post",
  "target_audience": "Women, 25-55, interested in beauty, wellness, and nutrition",
  "color_scheme": "Orange, white, warm, inviting",
  "text_density": "Moderate",
  "composition": "Product-focused",
  "cta_type": "Shop Now",
  "marketing_objective": "Conversion",
  "visual_style": "Playful",
  "special_elements": "Testimonial, product benefits (gluten-free, non-GMO, gelatin-free, plant-based, vegan), quantity (60 gummies)",
  "file_name": "personal_care_products_print_ads_60.jpg",
  "file_path": "D:/Developer/FunTime/AdGen/image-label/images/source\\personal care\\personal_care_products_print_ads_60.jpg",
  "width": 736,
  "height": 1104
}