{
  "dimensions": "489x693",
  "product_type": "Cats (Pet Adoption)",
  "brand_category": "Pet Shop / Adoption Service",
  "industry_category": "Pets",
  "ad_format": "Social Post",
  "target_audience": "Adults (25-55), Families, Pet Lovers",
  "color_scheme": "Orange, Yellow, White, Warm, Energetic",
  "text_density": "Moderate",
  "composition": "Product-focused",
  "cta_type": "Direct (Adopt Now!)",
  "marketing_objective": "Conversion",
  "visual_style": "Playful",
  "special_elements": "Offers (Adoption), Contact Information, Address",
  "file_name": "pet_product_print_ads_43.jpg",
  "file_path": "D:/Developer/FunTime/AdGen/image-label/images/source\\pets\\pet_product_print_ads_43.jpg",
  "width": 489,
  "height": 693
}