{
  "dimensions": "736x736",
  "product_type": "Voltage Stabilizer for Home Appliances",
  "brand_category": "Everest Home Appliances",
  "industry_category": "Electronics / Tech",
  "ad_format": "Social Post",
  "target_audience": "Adults (25-55), Homeowners, Individuals interested in appliance care and longevity",
  "color_scheme": "Blue, White, Gray, Clean, Calming",
  "text_density": "Moderate",
  "composition": "Product-focused, Stylized",
  "cta_type": "Visit Website",
  "marketing_objective": "Awareness",
  "visual_style": "Modern, Clean, Minimalist",
  "special_elements": "Website URL",
  "file_name": "service_print_ads_26.jpg",
  "file_path": "D:/Developer/FunTime/AdGen/image-label/images/source\\service\\service_print_ads_26.jpg",
  "width": 736,
  "height": 736
}