{
  "dimensions": "1874x2400",
  "product_type": "Washing Machine",
  "brand_category": "Currys PC World",
  "industry_category": "Retail / Marketplace",
  "ad_format": "Print Ad",
  "target_audience": "Adults (25-55), Homeowners, Tech-Savvy, Value-Seekers",
  "color_scheme": "White, Silver, Brown, Blue, Purple (logo), Clean, Minimalist",
  "text_density": "Minimal",
  "composition": "Product-focused, Conceptual",
  "cta_type": "Implied (Visit Store/Website)",
  "marketing_objective": "Awareness",
  "visual_style": "Playful, Conceptual, Minimalist",
  "special_elements": "Easter theme, Chocolate washing machine, Wrapped in foil",
  "file_name": "toys_print_ads_43.jpg",
  "file_path": "D:/Developer/FunTime/AdGen/image-label/images/source\\toys\\toys_print_ads_43.jpg",
  "width": 1874,
  "height": 2400
}